clickntrack/__init__.py
clickntrack/config.json
clickntrack/persistence.py
clickntrack/services.py
clickntrack/util.py
clickntrack/webservices.py
clickntrack-0.0.2.dev3.dist-info/LICENSE.txt
clickntrack-0.0.2.dev3.dist-info/METADATA
clickntrack-0.0.2.dev3.dist-info/WHEEL
clickntrack-0.0.2.dev3.dist-info/top_level.txt
clickntrack-0.0.2.dev3.dist-info/RECORD
