Metadata-Version: 2.1
Name: clickntrack
Version: 0.0.2.dev3
Summary: Click & Track services - REST API for short URL handling
Home-page: https://bitbucket.org/clickntrack/clickntrack-backend
Author: Xavier ROY
Author-email: xavier@regbuddy.eu
License: Apache License, Version 2.0
Keywords: URL shortener
Platform: UNKNOWN
Classifier: Programming Language :: Python
Classifier: Development Status :: 1 - Planning
Classifier: Operating System :: OS Independent
Classifier: Programming Language :: Python :: 3.6
Classifier: Topic :: Internet :: WWW/HTTP
Classifier: Intended Audience :: Developers
Requires-Dist: bottle (==0.12.16)
Requires-Dist: dnspython (==1.16.0)
Requires-Dist: monkey.dao (>=0.0.1.dev2)
Requires-Dist: monkey.dao.pymongo (>=0.0.1.dev2)
Requires-Dist: monkey.ioc (>=0.0.1.dev3)
Requires-Dist: pymongo (==3.7.2)
